odoo_resource_assessor/__init__.py
odoo_resource_assessor/resource_assessor.py
odoo_resource_assessor-0.2.0.dist-info/LICENSE
odoo_resource_assessor-0.2.0.dist-info/METADATA
odoo_resource_assessor-0.2.0.dist-info/WHEEL
odoo_resource_assessor-0.2.0.dist-info/entry_points.txt
odoo_resource_assessor-0.2.0.dist-info/top_level.txt
odoo_resource_assessor-0.2.0.dist-info/RECORD
