Metadata-Version: 2.1
Name: odoo-resource-assessor
Version: 0.2.0
Summary: A tool to calculate Odoo configuration based on system resources.
Home-page: https://git.coopdevs.org/coopdevs/sandbox/odoo_resource_assessor
Author: Lai
Author-email: sysadmin@coopdevs.org
License: MIT
Platform: UNKNOWN
Classifier: Programming Language :: Python :: 3
Classifier: Operating System :: OS Independent
Classifier: Intended Audience :: Developers
Classifier: Topic :: Software Development :: Build Tools
Classifier: Framework :: Odoo
Requires-Dist: psutil
